randommut/__init__.py
randommut/__main__.py
randommut/genome.py
randommut/muts.py
randommut/randomize.py
randommut/randommutworkflow.py
randommut/refseq.py
randommut-0.1.3.dist-info/LICENSE
randommut-0.1.3.dist-info/METADATA
randommut-0.1.3.dist-info/WHEEL
randommut-0.1.3.dist-info/entry_points.txt
randommut-0.1.3.dist-info/top_level.txt
randommut-0.1.3.dist-info/RECORD
