Metadata-Version: 2.1
Name: randommut
Version: 0.1.3
Summary: A package to randomze somatic mutaitons in the genome
Home-page: http://vm-ubuntu-dmp:3000/davidmasp/randommut
Author: David Mas
Author-email: david.mas@irbbarcelona.org
License: MIT
Platform: UNKNOWN
Requires-Dist: biopython
Requires-Dist: tqdm
Requires-Dist: numpy
Requires-Dist: pandas
